ckanext/__init__.py
ckanext/gallery/__init__.py
ckanext/gallery/lib/__init__.py
ckanext/gallery/lib/helpers.py
ckanext/gallery/logic/__init__.py
ckanext/gallery/logic/validators.py
ckanext/gallery/plugins/__init__.py
ckanext/gallery/plugins/gallery.py
ckanext/gallery/plugins/iiif.py
ckanext/gallery/plugins/image.py
ckanext/gallery/plugins/interfaces.py
ckanext/gallery/theme/assets/webassets.yml
ckanext/gallery/theme/assets/js/gallery.js
ckanext/gallery/theme/assets/less/gallery.less
ckanext/gallery/theme/assets/vendor/blueimp-gallery/Makefile
ckanext/gallery/theme/assets/vendor/blueimp-gallery/README.md
ckanext/gallery/theme/assets/vendor/blueimp-gallery/blueimp-gallery.jquery.json
ckanext/gallery/theme/assets/vendor/blueimp-gallery/bower.json
ckanext/gallery/theme/assets/vendor/blueimp-gallery/index.html
ckanext/gallery/theme/assets/vendor/blueimp-gallery/package.json
ckanext/gallery/theme/assets/vendor/blueimp-gallery/css/blueimp-gallery-indicator.css
ckanext/gallery/theme/assets/vendor/blueimp-gallery/css/blueimp-gallery-video.css
ckanext/gallery/theme/assets/vendor/blueimp-gallery/css/blueimp-gallery.css
ckanext/gallery/theme/assets/vendor/blueimp-gallery/css/blueimp-gallery.min.css
ckanext/gallery/theme/assets/vendor/blueimp-gallery/css/demo.css
ckanext/gallery/theme/assets/vendor/blueimp-gallery/img/error.png
ckanext/gallery/theme/assets/vendor/blueimp-gallery/img/error.svg
ckanext/gallery/theme/assets/vendor/blueimp-gallery/img/loading.gif
ckanext/gallery/theme/assets/vendor/blueimp-gallery/img/play-pause.png
ckanext/gallery/theme/assets/vendor/blueimp-gallery/img/play-pause.svg
ckanext/gallery/theme/assets/vendor/blueimp-gallery/img/video-play.png
ckanext/gallery/theme/assets/vendor/blueimp-gallery/img/video-play.svg
ckanext/gallery/theme/assets/vendor/blueimp-gallery/js/blueimp-gallery-fullscreen.js
ckanext/gallery/theme/assets/vendor/blueimp-gallery/js/blueimp-gallery-indicator.js
ckanext_gallery-3.0.6.dist-info/licenses/LICENSE
ckanext_gallery-3.0.6.dist-info/METADATA
ckanext_gallery-3.0.6.dist-info/WHEEL
ckanext_gallery-3.0.6.dist-info/entry_points.txt
ckanext_gallery-3.0.6.dist-info/top_level.txt
ckanext_gallery-3.0.6.dist-info/RECORD
